chaosopenstack/__init__.py
chaosopenstack/cli.py
chaosopenstack/utils.py
chaostoolkit_openstack-0.1.1.dist-info/AUTHORS.rst
chaostoolkit_openstack-0.1.1.dist-info/LICENSE
chaostoolkit_openstack-0.1.1.dist-info/METADATA
chaostoolkit_openstack-0.1.1.dist-info/WHEEL
chaostoolkit_openstack-0.1.1.dist-info/entry_points.txt
chaostoolkit_openstack-0.1.1.dist-info/top_level.txt
chaostoolkit_openstack-0.1.1.dist-info/RECORD
