Metadata-Version: 2.1
Name: chaostoolkit-openstack
Version: 0.1.1
Summary: Chaostoolkit driver for Openstack
Home-page: https://github.com/grubert65/chaostoolkit_openstack
Author: Marco Masetti
Author-email: marco.masetti@sky.uk
License: BSD license
Keywords: chaostoolkit_openstack
Platform: UNKNOWN
Classifier: Development Status :: 2 - Pre-Alpha
Classifier: Intended Audience :: Developers
Classifier: License :: OSI Approved :: BSD License
Classifier: Natural Language :: English
Classifier: Programming Language :: Python :: 2
Classifier: Programming Language :: Python :: 2.7
Classifier: Programming Language :: Python :: 3
Classifier: Programming Language :: Python :: 3.4
Classifier: Programming Language :: Python :: 3.5
Classifier: Programming Language :: Python :: 3.6
Classifier: Programming Language :: Python :: 3.7
Requires-Dist: pytest (==4.4.0)
Requires-Dist: chaostoolkit-lib (==1.1.2)
Requires-Dist: openstacksdk (==0.27.0)
Requires-Dist: logzero (==1.5.0)
